pygo/__init__.py
pygo/chan.py
pygo/chan_test.py
pygo/conftest.py
pygo/defer.py
pygo/defer_test.py
pygo/go.py
pygo/go_test.py
pygo/time.py
pygo/time_test.py
aio_pygo-1.0.2.dist-info/LICENSE
aio_pygo-1.0.2.dist-info/METADATA
aio_pygo-1.0.2.dist-info/WHEEL
aio_pygo-1.0.2.dist-info/top_level.txt
aio_pygo-1.0.2.dist-info/RECORD
