Metadata-Version: 2.1
Name: aio-pygo
Version: 1.0.2
Summary: Write Python code in a Go-like fashion.
Author: Gael Lz
Project-URL: Homepage, https://github.com/GaelLnz/pygo
Project-URL: Bug Tracker, https://github.com/GaelLnz/pygo/issues
Classifier: Programming Language :: Python :: 3
Classifier: License :: OSI Approved :: MIT License
Classifier: Operating System :: OS Independent
Requires-Python: >=3.10
License-File: LICENSE
